pymata_rh/__init__.py
pymata_rh/ina_219.py
pymata_rh/mpu_9250.py
pymata_rh/mpu_9250_constants.py
pymata_rh/pin_data.py
pymata_rh/private_constants.py
pymata_rh/pymata_rh.py
pymata_rh/rhgui.py
rh_tk_gui/__init__.py
rh_tk_gui/pymata_rh.py
rh_tk_gui/pymata_rh_support.py
rh_tk_gui/rh_tk_gui.py
rh_tk_gui/rh_tk_gui_support.py
robohat_gateway/__init__.py
robohat_gateway/robohat_gateway._save.py
robohat_gateway/robohat_gateway.py
pymata_rh-1.2.dist-info/METADATA
pymata_rh-1.2.dist-info/WHEEL
pymata_rh-1.2.dist-info/entry_points.txt
pymata_rh-1.2.dist-info/top_level.txt
pymata_rh-1.2.dist-info/RECORD
