Metadata-Version: 2.1
Name: pymata-rh
Version: 1.2
Summary: A Non-Blocking Event Driven Applications Framework
Home-page: https://github.com/MrYsLab/pymata_rh
Author: Alan Yorinks
Author-email: MisterYsLab@gmail.com
License: GNU Affero General Public License v3 or later (AGPLv3+)
Keywords: python banyan,RPC,Remote Procedure Call,Event Driven,Asynchronous,Non-Blocking,Raspberry Pi,ZeroMQ,MessagePack
Platform: UNKNOWN
Classifier: Development Status :: 5 - Production/Stable
Classifier: Environment :: Other Environment
Classifier: Intended Audience :: Education
Classifier: Intended Audience :: Developers
Classifier: License :: OSI Approved :: GNU Affero General Public License v3 or later (AGPLv3+)
Classifier: Operating System :: OS Independent
Classifier: Programming Language :: Python :: 3.7
Classifier: Topic :: Education
Classifier: Topic :: Software Development
Classifier: Topic :: Software Development :: Libraries :: Application Frameworks
Classifier: Topic :: System :: Hardware
Requires-Dist: pyserial
Requires-Dist: python-banyan (>=3.9)
